{"_links":{"self":{"href":"http://compras.dados.gov.br/compraSemLicitacao/doc/item_slicitacao/9002706001102008/itens.json","title":"Lista de itens da compra sem licitação"}},"_embedded":{"compras":[{"co_servico":17663,"no_servico":"CURSO APERFEICOAMENTO / ESPECIALIZACAO PROFISSIONAL","ds_detalhada":"Inscrição da servidora Thaís do Nascimento Amorim no \"Curso de Sistema de Registro de Preço Com Enfoque na Lei Complementar 123/06 Voltado às Aquisições Públicas\" a ser realizado no período de 23/06/2008 a 24/06/2008, nesta capital.","qt_material_alt":"1","no_unidade_medida":"un","vr_estimado":1380.00,"ds_tipo_fornecedor_vencedor":"PJ","nu_cnpj_vencedor":"07858757000160","_links":{"self":{"href":"/compraSemLicitacao/id/item_slicitacao/09002706001102008/itens/00000000010000017663","title":"Item  1 de compra sem licitação : servico"},"fornecedor":{"href":"/fornecedores/id/fornecedor_pj/07858757000160","title":"Fornecedor 07858757000160: 07858757000160"},"servico":{"href":"/servicos/id/servico/17663","title":"Servico 17663:  Código do Item - Serviço"}}}]},"count":1}