{"_links":{"self":{"href":"http://compras.dados.gov.br/compraSemLicitacao/doc/item_slicitacao/37307106000152004/itens.json","title":"Lista de itens da compra sem licitação"}},"_embedded":{"compras":[{"co_servico":3239,"no_servico":"TRANSPORTE RODOVIARIO - PESSOAL POR AUTOMOVEIS","ds_detalhada":"contratação de transporte rodoviário, com objetivo de atender deslocamento  devários Coordenadores Regionais de Projetos de Assentamento do Estado  de SantaCatarina, para participarem juntamente com INCRA e a UFSC, de Seminário  sobreGestão Pública em Projetos de Assentamento.","qt_material_alt":"1","no_unidade_medida":"u","vr_estimado":4500.00,"ds_tipo_fornecedor_vencedor":"PJ","nu_cnpj_vencedor":"00985027000180","_links":{"self":{"href":"/compraSemLicitacao/id/item_slicitacao/37307106000152004/itens/00000000010000003239","title":"Item  1 de compra sem licitação : servico"},"fornecedor":{"href":"/fornecedores/id/fornecedor_pj/00985027000180","title":"Fornecedor 00985027000180: 00985027000180"},"servico":{"href":"/servicos/id/servico/3239","title":"Servico 3239:  Código do Item - Serviço"}}}]},"count":1}