{"_links":{"self":{"href":"http://compras.dados.gov.br/compraSemLicitacao/doc/item_slicitacao/80301006015342017/itens.json","title":"Lista de itens da compra sem licitação"}},"_embedded":{"compras":[{"co_servico":17663,"no_servico":"CURSO APERFEICOAMENTO / ESPECIALIZACAO PROFISSIONAL","ds_detalhada":"Curso de inteligência artificial para 11 funcionários","qt_material_alt":"11","no_unidade_medida":"Unidade","vr_estimado":15960.00,"ds_tipo_fornecedor_vencedor":"PJ","nu_cnpj_vencedor":"13183890000166","_links":{"self":{"href":"/compraSemLicitacao/id/item_slicitacao/80301006015342017/itens/00000000010000017663","title":"Item  1 de compra sem licitação : servico"},"fornecedor":{"href":"/fornecedores/id/fornecedor_pj/13183890000166","title":"Fornecedor 13183890000166: 13183890000166"},"servico":{"href":"/servicos/id/servico/17663","title":"Servico 17663:  Código do Item - Serviço"}}}]},"count":1}