{"_links":{"self":{"href":"http://compras.dados.gov.br/compraSemLicitacao/doc/item_slicitacao/34400207000482011/itens.json","title":"Lista de itens da compra sem licitação"}},"_embedded":{"compras":[{"co_servico":17663,"no_servico":"CURSO APERFEICOAMENTO / ESPECIALIZACAO PROFISSIONAL","ds_detalhada":"Contratação de museóloga e professora, para ministrar o módulo 06 - MuseologiaSocial e novos modelos de comunicação, com 9 horas/aula, nos dias 09 à  20/07/2011,promovido pela Diretoria de Documentação/MUHNE/FUNDAJ.","qt_material_alt":"1","no_unidade_medida":"parcela","vr_estimado":3000.00,"ds_tipo_fornecedor_vencedor":"PF","nu_cpf_vencedor":"***.689.708-**","_links":{"self":{"href":"/compraSemLicitacao/id/item_slicitacao/34400207000482011/itens/00000000010000017663","title":"Item  1 de compra sem licitação : servico"},"fornecedor":{"href":"/fornecedores/id/fornecedor_pf/255849","title":"Fornecedor ***.689.708-**: 255849: MARILIA XAVIER CURY              -"},"servico":{"href":"/servicos/id/servico/17663","title":"Servico 17663:  Código do Item - Serviço"}}}]},"count":1}