{"_links":{"self":{"href":"http://compras.dados.gov.br/licitacoes/doc/licitacao/92562405000112016/itens.json","title":"Lista de itens da licitação"},"first":{"href":"/licitacoes/doc/licitacao/92562405000112016/itens.json?offset=0","title":"Primeira página"}},"_embedded":{"itensLicitacao":[{"uasg":925624,"modalidade":5,"numero_aviso":112016,"numero_licitacao":"92562405000112016","numero_item_licitacao":1,"codigo_item_servico":582,"descricao_item":"TRANSMISSÃO DOS DADOS DAS ESTAÇÕES SISMOGRÁFICAS DA RSISNE: O SERVIÇO A SER RE COMUNICAÇÕES;? ATUALIZAÇÃO E EVOLUÇÃO TECNOLÓGICA;? MELHORIA DE QUALIDADE E PR ODUTIVIDADE EM TELECOMUNICAÇÕES;? MAIOR AGILIDADE EM PLANEJAMENTO, MUDANÇAS, C ONTRATAÇÕES E MANUTENÇÕES;? FLEXIBILIDADE NO USO DE RECURSOS, CONFORME AS NECE SSIDADES;? CAPACITAÇÃO TÉCNICA E OPERACIONAL DE PESSOAL (RH);? GERENCIAMENTO P RÓ-ATIVO CENTRALIZADO DA ESTRUTURA DE TELECOMUNICAÇÕES E COM ? GARANTIA DE DIS PONIBILIDADE E SEGURANÇA. ALIZADO CONSISTE NO FORNECIMENTO DE UMA INFRAESTRUTURA DE TELECOMUNICAÇÕES ENT RE AS ESTAÇÕES SISMOGRÁFICAS INSTALADAS PELA REGIÃO NORDESTE DO BRASIL ATRAVÉS  DO PROJETO DA RSISNE  PELOS TÉCNICOS DO LABORATÓRIO SISMOLÓGICO DA UNIVERSIDA DE FEDERAL DO RIO GRANDE DO NORTE, PERMITINDO UM ACOMPANHAMENTO EM TEMPO QUASE -REAL DA ATIVIDADE SÍSMICA DA REGIÃO NORDESTE. ? SUPORTE ÀS NECESSIDADES ATUAI S E FLEXIBILIDADE PARA FUTURAS EXPANSÕES;? PADRONIZAÇÃO E CONVERGÊNCIA DE TECN OLOGIAS E DE SERVIÇOS;? REDE CORPORATIVA DE TELECOMUNICAÇÕES DE ALTO DESEMPENH O E SEGURANÇA;? GARANTIA DE EFICIÊNCIA E OTIMIZAÇÃO DE CUSTOS / BUDGET EM TELE","quantidade":"1","unidade":"Unidade","cnpj_fornecedor":"09056811000189","cpfVencedor":"","beneficio":"Nao possui tratamento diferenciado para ME/EPP/COOPERATIVA","valor_estimado":80159.99,"decreto_7174":false,"criterio_julgamento":"Menor Valor","_links":{"self":{"href":"/licitacoes/doc/licitacao/92562405000112016/itens/1","title":"Item 1 da licitação 92562405000112016"},"fornecedor":{"href":"/fornecedores/id/fornecedor_pj/09056811000189","title":"Fornecedor 09056811000189: NET.COM TELECOMUNICACOES LTDA - EPP"},"licitacao":{"href":"/licitacoes/id/licitacao/92562405000112016","title":"Licitação 92562405000112016"},"modalidade_licitacao":{"href":"/licitacoes/id/modalidade_licitacao/5","title":"Modalidade de Licitação 5: PREGÃO                                            "},"servico":{"href":"/servicos/id/servico/582","title":"Servico 582: ESTUDOS E PROJETOS DE TELECOMUNICACOES - TRANSMISSAO                                                                    "},"uasg":{"href":"/licitacoes/id/uasg/925624","title":"UASG 925624: FUND. NORTERIOGRANDENSE DE PESQ. E CULTURA"}}}]},"count":1}