{"_links":{"self":{"href":"http://compras.dados.gov.br/licitacoes/doc/licitacao/07000405000632014/itens.json","title":"Lista de itens da licitação"},"first":{"href":"/licitacoes/doc/licitacao/07000405000632014/itens.json?offset=0","title":"Primeira página"}},"_embedded":{"itensLicitacao":[{"uasg":70004,"modalidade":5,"numero_aviso":632014,"numero_licitacao":"07000405000632014","numero_item_licitacao":1,"codigo_item_servico":213,"descricao_item":"Projeto de Instalações Elétricas.","quantidade":"1","unidade":"Serviço","cnpj_fornecedor":"13473150000164","cpfVencedor":"","beneficio":"Nao possui tratamento diferenciado para ME/EPP/COOPERATIVA","valor_estimado":700.00,"decreto_7174":false,"criterio_julgamento":"Menor Valor","_links":{"self":{"href":"/licitacoes/doc/licitacao/07000405000632014/itens/1","title":"Item 1 da licitação 07000405000632014"},"fornecedor":{"href":"/fornecedores/id/fornecedor_pj/13473150000164","title":"Fornecedor 13473150000164: ETI INSTALACAO E MANUTENCAO EIRELI - ME"},"licitacao":{"href":"/licitacoes/id/licitacao/07000405000632014","title":"Licitação 07000405000632014"},"modalidade_licitacao":{"href":"/licitacoes/id/modalidade_licitacao/5","title":"Modalidade de Licitação 5: PREGÃO                                            "},"servico":{"href":"/servicos/id/servico/213","title":"Servico 213: ESTUDOS E PROJETOS DE INSTALACAO ELETRICA                                                                               "},"uasg":{"href":"/licitacoes/id/uasg/70004","title":"UASG 70004: TRIBUNAL REGIONAL ELEITORAL DO PARA"}}},{"uasg":70004,"modalidade":5,"numero_aviso":632014,"numero_licitacao":"07000405000632014","numero_item_licitacao":2,"codigo_item_servico":230,"descricao_item":"Projeto de Cabeamento Estruturado (rede lógica e telefone).","quantidade":"1","unidade":"Serviço","cnpj_fornecedor":"13473150000164","cpfVencedor":"","beneficio":"Nao possui tratamento diferenciado para ME/EPP/COOPERATIVA","valor_estimado":400.00,"decreto_7174":false,"criterio_julgamento":"Menor Valor","_links":{"self":{"href":"/licitacoes/doc/licitacao/07000405000632014/itens/2","title":"Item 2 da licitação 07000405000632014"},"fornecedor":{"href":"/fornecedores/id/fornecedor_pj/13473150000164","title":"Fornecedor 13473150000164: ETI INSTALACAO E MANUTENCAO EIRELI - ME"},"licitacao":{"href":"/licitacoes/id/licitacao/07000405000632014","title":"Licitação 07000405000632014"},"modalidade_licitacao":{"href":"/licitacoes/id/modalidade_licitacao/5","title":"Modalidade de Licitação 5: PREGÃO                                            "},"servico":{"href":"/servicos/id/servico/230","title":"Servico 230: ESTUDOS E PROJETOS DE INSTALACAO TELEFONICA                                                                             "},"uasg":{"href":"/licitacoes/id/uasg/70004","title":"UASG 70004: TRIBUNAL REGIONAL ELEITORAL DO PARA"}}},{"uasg":70004,"modalidade":5,"numero_aviso":632014,"numero_licitacao":"07000405000632014","numero_item_licitacao":3,"codigo_item_servico":523,"descricao_item":"Projeto de Detecção, Alarme e Combate a Incêndio.","quantidade":"1","unidade":"Serviço","cnpj_fornecedor":"13473150000164","cpfVencedor":"","beneficio":"Nao possui tratamento diferenciado para ME/EPP/COOPERATIVA","valor_estimado":3500.00,"decreto_7174":false,"criterio_julgamento":"Menor Valor","_links":{"self":{"href":"/licitacoes/doc/licitacao/07000405000632014/itens/3","title":"Item 3 da licitação 07000405000632014"},"fornecedor":{"href":"/fornecedores/id/fornecedor_pj/13473150000164","title":"Fornecedor 13473150000164: ETI INSTALACAO E MANUTENCAO EIRELI - ME"},"licitacao":{"href":"/licitacoes/id/licitacao/07000405000632014","title":"Licitação 07000405000632014"},"modalidade_licitacao":{"href":"/licitacoes/id/modalidade_licitacao/5","title":"Modalidade de Licitação 5: PREGÃO                                            "},"servico":{"href":"/servicos/id/servico/523","title":"Servico 523: ESTUDOS E PROJETOS DE SISTEMAS DE PROTECAO CONTRA INCENDIO                                                              "},"uasg":{"href":"/licitacoes/id/uasg/70004","title":"UASG 70004: TRIBUNAL REGIONAL ELEITORAL DO PARA"}}},{"uasg":70004,"modalidade":5,"numero_aviso":632014,"numero_licitacao":"07000405000632014","numero_item_licitacao":4,"codigo_item_servico":14010,"descricao_item":"Projeto de Circuito Fechado de TV (vigilância).","quantidade":"1","unidade":"Serviço","cnpj_fornecedor":"13473150000164","cpfVencedor":"","beneficio":"Nao possui tratamento diferenciado para ME/EPP/COOPERATIVA","valor_estimado":2499.00,"decreto_7174":false,"criterio_julgamento":"Menor Valor","_links":{"self":{"href":"/licitacoes/doc/licitacao/07000405000632014/itens/4","title":"Item 4 da licitação 07000405000632014"},"fornecedor":{"href":"/fornecedores/id/fornecedor_pj/13473150000164","title":"Fornecedor 13473150000164: ETI INSTALACAO E MANUTENCAO EIRELI - ME"},"licitacao":{"href":"/licitacoes/id/licitacao/07000405000632014","title":"Licitação 07000405000632014"},"modalidade_licitacao":{"href":"/licitacoes/id/modalidade_licitacao/5","title":"Modalidade de Licitação 5: PREGÃO                                            "},"servico":{"href":"/servicos/id/servico/14010","title":"Servico 14010: INFORMATICA - ESTUDO E PROJETO DE INSTALACOES FISICAS                                                                   "},"uasg":{"href":"/licitacoes/id/uasg/70004","title":"UASG 70004: TRIBUNAL REGIONAL ELEITORAL DO PARA"}}},{"uasg":70004,"modalidade":5,"numero_aviso":632014,"numero_licitacao":"07000405000632014","numero_item_licitacao":5,"codigo_item_servico":574,"descricao_item":"Projeto de Proteção contra Descargas Atmosféricas.","quantidade":"1","unidade":"Serviço","cnpj_fornecedor":"13473150000164","cpfVencedor":"","beneficio":"Nao possui tratamento diferenciado para ME/EPP/COOPERATIVA","valor_estimado":2998.00,"decreto_7174":false,"criterio_julgamento":"Menor Valor","_links":{"self":{"href":"/licitacoes/doc/licitacao/07000405000632014/itens/5","title":"Item 5 da licitação 07000405000632014"},"fornecedor":{"href":"/fornecedores/id/fornecedor_pj/13473150000164","title":"Fornecedor 13473150000164: ETI INSTALACAO E MANUTENCAO EIRELI - ME"},"licitacao":{"href":"/licitacoes/id/licitacao/07000405000632014","title":"Licitação 07000405000632014"},"modalidade_licitacao":{"href":"/licitacoes/id/modalidade_licitacao/5","title":"Modalidade de Licitação 5: PREGÃO                                            "},"servico":{"href":"/servicos/id/servico/574","title":"Servico 574: ESTUDOS E PROJETOS DE SISTEMAS DE ATERRAMENTO E PROTECAO CONTRA DESCARGAS ATMOSFERICAS                                  "},"uasg":{"href":"/licitacoes/id/uasg/70004","title":"UASG 70004: TRIBUNAL REGIONAL ELEITORAL DO PARA"}}},{"uasg":70004,"modalidade":5,"numero_aviso":632014,"numero_licitacao":"07000405000632014","numero_item_licitacao":6,"codigo_item_servico":507,"descricao_item":"Projeto de Climatização.","quantidade":"1","unidade":"Serviço","cnpj_fornecedor":"13473150000164","cpfVencedor":"","beneficio":"Nao possui tratamento diferenciado para ME/EPP/COOPERATIVA","valor_estimado":3000.00,"decreto_7174":false,"criterio_julgamento":"Menor Valor","_links":{"self":{"href":"/licitacoes/doc/licitacao/07000405000632014/itens/6","title":"Item 6 da licitação 07000405000632014"},"fornecedor":{"href":"/fornecedores/id/fornecedor_pj/13473150000164","title":"Fornecedor 13473150000164: ETI INSTALACAO E MANUTENCAO EIRELI - ME"},"licitacao":{"href":"/licitacoes/id/licitacao/07000405000632014","title":"Licitação 07000405000632014"},"modalidade_licitacao":{"href":"/licitacoes/id/modalidade_licitacao/5","title":"Modalidade de Licitação 5: PREGÃO                                            "},"servico":{"href":"/servicos/id/servico/507","title":"Servico 507: ESTUDOS E PROJETOS DE SISTEMAS DE REFRIGERACAO                                                                          "},"uasg":{"href":"/licitacoes/id/uasg/70004","title":"UASG 70004: TRIBUNAL REGIONAL ELEITORAL DO PARA"}}},{"uasg":70004,"modalidade":5,"numero_aviso":632014,"numero_licitacao":"07000405000632014","numero_item_licitacao":7,"codigo_item_servico":20060,"descricao_item":"Elaboração de Orçamento Estimativo.","quantidade":"1","unidade":"Serviço","cnpj_fornecedor":"13473150000164","cpfVencedor":"","beneficio":"Nao possui tratamento diferenciado para ME/EPP/COOPERATIVA","valor_estimado":1987.00,"decreto_7174":false,"criterio_julgamento":"Menor Valor","_links":{"self":{"href":"/licitacoes/doc/licitacao/07000405000632014/itens/7","title":"Item 7 da licitação 07000405000632014"},"fornecedor":{"href":"/fornecedores/id/fornecedor_pj/13473150000164","title":"Fornecedor 13473150000164: ETI INSTALACAO E MANUTENCAO EIRELI - ME"},"licitacao":{"href":"/licitacoes/id/licitacao/07000405000632014","title":"Licitação 07000405000632014"},"modalidade_licitacao":{"href":"/licitacoes/id/modalidade_licitacao/5","title":"Modalidade de Licitação 5: PREGÃO                                            "},"servico":{"href":"/servicos/id/servico/20060","title":"Servico 20060: ELABORACAO / ANALISE PROJETO - ENGENHARIA                                                                               "},"uasg":{"href":"/licitacoes/id/uasg/70004","title":"UASG 70004: TRIBUNAL REGIONAL ELEITORAL DO PARA"}}}]},"count":7}