{"_links":{"self":{"href":"http://compras.dados.gov.br/licitacoes/doc/licitacao/19300101000022007/itens.json","title":"Lista de itens da licitação"},"first":{"href":"/licitacoes/doc/licitacao/19300101000022007/itens.json?offset=0","title":"Primeira página"}},"_embedded":{"itensLicitacao":[{"uasg":193001,"modalidade":1,"numero_aviso":22007,"numero_licitacao":"19300101000022007","numero_item_licitacao":1,"codigo_item_servico":299,"descricao_item":"Fornecimento e instalação de DESSSALINIZADOR, com vazão de 7.0001/h, para tend er a localidade Povoado Carnaibas, municipio de Campo Grande-PI.","quantidade":"1","unidade":"UNI","cpfVencedor":"","beneficio":"Nao possui tratamento diferenciado para ME/EPP/COOPERATIVA","valor_estimado":0.00,"decreto_7174":false,"criterio_julgamento":"Menor Valor","_links":{"self":{"href":"/licitacoes/doc/licitacao/19300101000022007/itens/1","title":"Item 1 da licitação 19300101000022007"},"licitacao":{"href":"/licitacoes/id/licitacao/19300101000022007","title":"Licitação 19300101000022007"},"modalidade_licitacao":{"href":"/licitacoes/id/modalidade_licitacao/1","title":"Modalidade de Licitação 1: CONVITE                                           "},"servico":{"href":"/servicos/id/servico/299","title":"Servico 299: ESTUDOS E PROJETOS DE SANEAMENTO - TRATAMENTO DE AGUA                                                                   "},"uasg":{"href":"/licitacoes/id/uasg/193001","title":"UASG 193001: DNOCS 1A.DR - TERESINA-PI"}}}]},"count":1}