{"_links":{"self":{"href":"http://compras.dados.gov.br/licitacoes/doc/licitacao/34400205000092014/itens.json","title":"Lista de itens da licitação"},"first":{"href":"/licitacoes/doc/licitacao/34400205000092014/itens.json?offset=0","title":"Primeira página"}},"_embedded":{"itensLicitacao":[{"uasg":344002,"modalidade":5,"numero_aviso":92014,"numero_licitacao":"34400205000092014","numero_item_licitacao":1,"codigo_item_servico":264,"descricao_item":"Desenvolvimento de projeto de instalações elétricas, hidráulicas, cabeamento e struturado e planilha orçamentária para reforma dos edifícios da Fundação Joaq uim Nabuco.","quantidade":"1","unidade":"un","cnpj_fornecedor":"14180300000104","cpfVencedor":"","beneficio":"Beneficio Tipo I - Participacao Exclusiva de ME/EPP/COOPERATIVA","valor_estimado":19989.99,"decreto_7174":false,"criterio_julgamento":"Menor Valor","_links":{"self":{"href":"/licitacoes/doc/licitacao/34400205000092014/itens/1","title":"Item 1 da licitação 34400205000092014"},"fornecedor":{"href":"/fornecedores/id/fornecedor_pj/14180300000104","title":"Fornecedor 14180300000104: T & P ENGENHARIA LTDA - EPP"},"licitacao":{"href":"/licitacoes/id/licitacao/34400205000092014","title":"Licitação 34400205000092014"},"modalidade_licitacao":{"href":"/licitacoes/id/modalidade_licitacao/5","title":"Modalidade de Licitação 5: PREGÃO                                            "},"servico":{"href":"/servicos/id/servico/264","title":"Servico 264: ESTUDOS E PROJETOS - INSTALACOES PREDIAIS                                                                               "},"uasg":{"href":"/licitacoes/id/uasg/344002","title":"UASG 344002: FUNDACAO JOAQUIM NABUCO / MEC / PE"}}}]},"count":1}