{"_links":{"self":{"href":"http://compras.dados.gov.br/licitacoes/doc/irp/153079000812010/itens.json","title":"Lista de itens da intenção de registro de preço"},"first":{"href":"/licitacoes/doc/irp/153079000812010/itens.json?offset=0","title":"Primeira página"}},"_embedded":{"itensIrp":[{"uasg":153079,"numero_irp":812010,"numero_item":1,"id_irp":"153079000812010","modalidade_licitacao_item":5,"criterio_julgamento":"Menor Valor","codigo_material":150481,"descricao_detalhada":"ARMÁRIO ESCRITÓRIO, NOME ARMÁRIO ESCRITÓRIO","tipo":"Material","unidade_fornecimento":"un                  ","valor_estimado":"600.2400","_links":{"self":{"href":"/licitacoes/id/irp/153079000812010/itens/1","title":"Item 1 da intenção de registro de preço: 153079000812010"},"irp":{"href":"/licitacoes/id/irp/153079000812010","title":"Irp 153079000812010"},"material":{"href":"/materiais/id/material/150481","title":"Material 150481: null"},"modalidade_licitacao":{"href":"/licitacoes/id/modalidade_licitacao/5","title":"Modalidade de Licitação 5: PREGÃO                                            "},"participantes":{"href":"/licitacoes/id/irp/153079000812010/itens/1/participantes","title":"Participantes do Item de IRP"},"uasg":{"href":"/licitacoes/id/uasg/153079","title":"UASG 153079: UNIVERSIDADE FEDERAL DO PARANA"}}},{"uasg":153079,"numero_irp":812010,"numero_item":2,"id_irp":"153079000812010","modalidade_licitacao_item":5,"criterio_julgamento":"Menor Valor","codigo_material":150481,"descricao_detalhada":"ARMÁRIO ESCRITÓRIO, NOME ARMÁRIO ESCRITÓRIO","tipo":"Material","unidade_fornecimento":"un                  ","valor_estimado":"531.9700","_links":{"self":{"href":"/licitacoes/id/irp/153079000812010/itens/2","title":"Item 2 da intenção de registro de preço: 153079000812010"},"irp":{"href":"/licitacoes/id/irp/153079000812010","title":"Irp 153079000812010"},"material":{"href":"/materiais/id/material/150481","title":"Material 150481: null"},"modalidade_licitacao":{"href":"/licitacoes/id/modalidade_licitacao/5","title":"Modalidade de Licitação 5: PREGÃO                                            "},"participantes":{"href":"/licitacoes/id/irp/153079000812010/itens/2/participantes","title":"Participantes do Item de IRP"},"uasg":{"href":"/licitacoes/id/uasg/153079","title":"UASG 153079: UNIVERSIDADE FEDERAL DO PARANA"}}},{"uasg":153079,"numero_irp":812010,"numero_item":3,"id_irp":"153079000812010","modalidade_licitacao_item":5,"criterio_julgamento":"Menor Valor","codigo_material":150481,"descricao_detalhada":"ARMÁRIO ESCRITÓRIO, NOME ARMÁRIO ESCRITÓRIO","tipo":"Material","unidade_fornecimento":"un                  ","valor_estimado":"372.9400","_links":{"self":{"href":"/licitacoes/id/irp/153079000812010/itens/3","title":"Item 3 da intenção de registro de preço: 153079000812010"},"irp":{"href":"/licitacoes/id/irp/153079000812010","title":"Irp 153079000812010"},"material":{"href":"/materiais/id/material/150481","title":"Material 150481: null"},"modalidade_licitacao":{"href":"/licitacoes/id/modalidade_licitacao/5","title":"Modalidade de Licitação 5: PREGÃO                                            "},"participantes":{"href":"/licitacoes/id/irp/153079000812010/itens/3/participantes","title":"Participantes do Item de IRP"},"uasg":{"href":"/licitacoes/id/uasg/153079","title":"UASG 153079: UNIVERSIDADE FEDERAL DO PARANA"}}},{"uasg":153079,"numero_irp":812010,"numero_item":4,"id_irp":"153079000812010","modalidade_licitacao_item":5,"criterio_julgamento":"Menor Valor","codigo_material":150481,"descricao_detalhada":"ARMÁRIO ESCRITÓRIO, NOME ARMÁRIO ESCRITÓRIO","tipo":"Material","unidade_fornecimento":"un                  ","valor_estimado":"764.6700","_links":{"self":{"href":"/licitacoes/id/irp/153079000812010/itens/4","title":"Item 4 da intenção de registro de preço: 153079000812010"},"irp":{"href":"/licitacoes/id/irp/153079000812010","title":"Irp 153079000812010"},"material":{"href":"/materiais/id/material/150481","title":"Material 150481: null"},"modalidade_licitacao":{"href":"/licitacoes/id/modalidade_licitacao/5","title":"Modalidade de Licitação 5: PREGÃO                                            "},"participantes":{"href":"/licitacoes/id/irp/153079000812010/itens/4/participantes","title":"Participantes do Item de IRP"},"uasg":{"href":"/licitacoes/id/uasg/153079","title":"UASG 153079: UNIVERSIDADE FEDERAL DO PARANA"}}},{"uasg":153079,"numero_irp":812010,"numero_item":5,"id_irp":"153079000812010","modalidade_licitacao_item":5,"criterio_julgamento":"Menor Valor","codigo_material":150481,"descricao_detalhada":"ARMÁRIO ESCRITÓRIO, NOME ARMÁRIO ESCRITÓRIO","tipo":"Material","unidade_fornecimento":"un                  ","valor_estimado":"643.3300","_links":{"self":{"href":"/licitacoes/id/irp/153079000812010/itens/5","title":"Item 5 da intenção de registro de preço: 153079000812010"},"irp":{"href":"/licitacoes/id/irp/153079000812010","title":"Irp 153079000812010"},"material":{"href":"/materiais/id/material/150481","title":"Material 150481: null"},"modalidade_licitacao":{"href":"/licitacoes/id/modalidade_licitacao/5","title":"Modalidade de Licitação 5: PREGÃO                                            "},"participantes":{"href":"/licitacoes/id/irp/153079000812010/itens/5/participantes","title":"Participantes do Item de IRP"},"uasg":{"href":"/licitacoes/id/uasg/153079","title":"UASG 153079: UNIVERSIDADE FEDERAL DO PARANA"}}},{"uasg":153079,"numero_irp":812010,"numero_item":6,"id_irp":"153079000812010","modalidade_licitacao_item":5,"criterio_julgamento":"Menor Valor","codigo_material":150481,"descricao_detalhada":"ARMÁRIO ESCRITÓRIO, NOME ARMÁRIO ESCRITÓRIO","tipo":"Material","unidade_fornecimento":"un                  ","valor_estimado":"655.6700","_links":{"self":{"href":"/licitacoes/id/irp/153079000812010/itens/6","title":"Item 6 da intenção de registro de preço: 153079000812010"},"irp":{"href":"/licitacoes/id/irp/153079000812010","title":"Irp 153079000812010"},"material":{"href":"/materiais/id/material/150481","title":"Material 150481: null"},"modalidade_licitacao":{"href":"/licitacoes/id/modalidade_licitacao/5","title":"Modalidade de Licitação 5: PREGÃO                                            "},"participantes":{"href":"/licitacoes/id/irp/153079000812010/itens/6/participantes","title":"Participantes do Item de IRP"},"uasg":{"href":"/licitacoes/id/uasg/153079","title":"UASG 153079: UNIVERSIDADE FEDERAL DO PARANA"}}},{"uasg":153079,"numero_irp":812010,"numero_item":7,"id_irp":"153079000812010","modalidade_licitacao_item":5,"criterio_julgamento":"Menor Valor","codigo_material":150505,"descricao_detalhada":"ARQUIVO ESCRITÓRIO, NOME ARQUIVO ESCRITÓRIO","tipo":"Material","unidade_fornecimento":"un                  ","valor_estimado":"303.3300","_links":{"self":{"href":"/licitacoes/id/irp/153079000812010/itens/7","title":"Item 7 da intenção de registro de preço: 153079000812010"},"irp":{"href":"/licitacoes/id/irp/153079000812010","title":"Irp 153079000812010"},"material":{"href":"/materiais/id/material/150505","title":"Material 150505: null"},"modalidade_licitacao":{"href":"/licitacoes/id/modalidade_licitacao/5","title":"Modalidade de Licitação 5: PREGÃO                                            "},"participantes":{"href":"/licitacoes/id/irp/153079000812010/itens/7/participantes","title":"Participantes do Item de IRP"},"uasg":{"href":"/licitacoes/id/uasg/153079","title":"UASG 153079: UNIVERSIDADE FEDERAL DO PARANA"}}},{"uasg":153079,"numero_irp":812010,"numero_item":8,"id_irp":"153079000812010","modalidade_licitacao_item":5,"criterio_julgamento":"Menor Valor","codigo_material":116700,"descricao_detalhada":"BALCÃO, NOME BALCAO MADEIRA","tipo":"Material","unidade_fornecimento":"un                  ","valor_estimado":"314.6700","_links":{"self":{"href":"/licitacoes/id/irp/153079000812010/itens/8","title":"Item 8 da intenção de registro de preço: 153079000812010"},"irp":{"href":"/licitacoes/id/irp/153079000812010","title":"Irp 153079000812010"},"material":{"href":"/materiais/id/material/116700","title":"Material 116700: null"},"modalidade_licitacao":{"href":"/licitacoes/id/modalidade_licitacao/5","title":"Modalidade de Licitação 5: PREGÃO                                            "},"participantes":{"href":"/licitacoes/id/irp/153079000812010/itens/8/participantes","title":"Participantes do Item de IRP"},"uasg":{"href":"/licitacoes/id/uasg/153079","title":"UASG 153079: UNIVERSIDADE FEDERAL DO PARANA"}}},{"uasg":153079,"numero_irp":812010,"numero_item":9,"id_irp":"153079000812010","modalidade_licitacao_item":5,"criterio_julgamento":"Menor Valor","codigo_material":150443,"descricao_detalhada":"BANCADA, NOME BANCADA","tipo":"Material","unidade_fornecimento":"un                  ","valor_estimado":"535.7700","_links":{"self":{"href":"/licitacoes/id/irp/153079000812010/itens/9","title":"Item 9 da intenção de registro de preço: 153079000812010"},"irp":{"href":"/licitacoes/id/irp/153079000812010","title":"Irp 153079000812010"},"material":{"href":"/materiais/id/material/150443","title":"Material 150443: null"},"modalidade_licitacao":{"href":"/licitacoes/id/modalidade_licitacao/5","title":"Modalidade de Licitação 5: PREGÃO                                            "},"participantes":{"href":"/licitacoes/id/irp/153079000812010/itens/9/participantes","title":"Participantes do Item de IRP"},"uasg":{"href":"/licitacoes/id/uasg/153079","title":"UASG 153079: UNIVERSIDADE FEDERAL DO PARANA"}}},{"uasg":153079,"numero_irp":812010,"numero_item":10,"id_irp":"153079000812010","modalidade_licitacao_item":5,"criterio_julgamento":"Menor Valor","codigo_material":74829,"descricao_detalhada":"BANQUETA, NOME BANQUETA FIXA","tipo":"Material","unidade_fornecimento":"un                  ","valor_estimado":"31.9300","_links":{"self":{"href":"/licitacoes/id/irp/153079000812010/itens/10","title":"Item 10 da intenção de registro de preço: 153079000812010"},"irp":{"href":"/licitacoes/id/irp/153079000812010","title":"Irp 153079000812010"},"material":{"href":"/materiais/id/material/74829","title":"Material 74829: null"},"modalidade_licitacao":{"href":"/licitacoes/id/modalidade_licitacao/5","title":"Modalidade de Licitação 5: PREGÃO                                            "},"participantes":{"href":"/licitacoes/id/irp/153079000812010/itens/10/participantes","title":"Participantes do Item de IRP"},"uasg":{"href":"/licitacoes/id/uasg/153079","title":"UASG 153079: UNIVERSIDADE FEDERAL DO PARANA"}}},{"uasg":153079,"numero_irp":812010,"numero_item":11,"id_irp":"153079000812010","modalidade_licitacao_item":5,"criterio_julgamento":"Menor Valor","codigo_material":74829,"descricao_detalhada":"BANQUETA, NOME BANQUETA FIXA","tipo":"Material","unidade_fornecimento":"un                  ","valor_estimado":"61.0000","_links":{"self":{"href":"/licitacoes/id/irp/153079000812010/itens/11","title":"Item 11 da intenção de registro de preço: 153079000812010"},"irp":{"href":"/licitacoes/id/irp/153079000812010","title":"Irp 153079000812010"},"material":{"href":"/materiais/id/material/74829","title":"Material 74829: null"},"modalidade_licitacao":{"href":"/licitacoes/id/modalidade_licitacao/5","title":"Modalidade de Licitação 5: PREGÃO                                            "},"participantes":{"href":"/licitacoes/id/irp/153079000812010/itens/11/participantes","title":"Participantes do Item de IRP"},"uasg":{"href":"/licitacoes/id/uasg/153079","title":"UASG 153079: UNIVERSIDADE FEDERAL DO PARANA"}}},{"uasg":153079,"numero_irp":812010,"numero_item":12,"id_irp":"153079000812010","modalidade_licitacao_item":5,"criterio_julgamento":"Menor Valor","codigo_material":20680,"descricao_detalhada":"CADEIRA ESCRITÓRIO, NOME CADEIRA ESCRITORIO","tipo":"Material","unidade_fornecimento":"un                  ","valor_estimado":"270.3800","_links":{"self":{"href":"/licitacoes/id/irp/153079000812010/itens/12","title":"Item 12 da intenção de registro de preço: 153079000812010"},"irp":{"href":"/licitacoes/id/irp/153079000812010","title":"Irp 153079000812010"},"material":{"href":"/materiais/id/material/20680","title":"Material 20680: null"},"modalidade_licitacao":{"href":"/licitacoes/id/modalidade_licitacao/5","title":"Modalidade de Licitação 5: PREGÃO                                            "},"participantes":{"href":"/licitacoes/id/irp/153079000812010/itens/12/participantes","title":"Participantes do Item de IRP"},"uasg":{"href":"/licitacoes/id/uasg/153079","title":"UASG 153079: UNIVERSIDADE FEDERAL DO PARANA"}}},{"uasg":153079,"numero_irp":812010,"numero_item":13,"id_irp":"153079000812010","modalidade_licitacao_item":5,"criterio_julgamento":"Menor Valor","codigo_material":20680,"descricao_detalhada":"CADEIRA ESCRITÓRIO, NOME CADEIRA ESCRITORIO","tipo":"Material","unidade_fornecimento":"un                  ","valor_estimado":"72.6700","_links":{"self":{"href":"/licitacoes/id/irp/153079000812010/itens/13","title":"Item 13 da intenção de registro de preço: 153079000812010"},"irp":{"href":"/licitacoes/id/irp/153079000812010","title":"Irp 153079000812010"},"material":{"href":"/materiais/id/material/20680","title":"Material 20680: null"},"modalidade_licitacao":{"href":"/licitacoes/id/modalidade_licitacao/5","title":"Modalidade de Licitação 5: PREGÃO                                            "},"participantes":{"href":"/licitacoes/id/irp/153079000812010/itens/13/participantes","title":"Participantes do Item de IRP"},"uasg":{"href":"/licitacoes/id/uasg/153079","title":"UASG 153079: UNIVERSIDADE FEDERAL DO PARANA"}}},{"uasg":153079,"numero_irp":812010,"numero_item":14,"id_irp":"153079000812010","modalidade_licitacao_item":5,"criterio_julgamento":"Menor Valor","codigo_material":20680,"descricao_detalhada":"CADEIRA ESCRITÓRIO, NOME CADEIRA ESCRITORIO","tipo":"Material","unidade_fornecimento":"un                  ","valor_estimado":"72.6600","_links":{"self":{"href":"/licitacoes/id/irp/153079000812010/itens/14","title":"Item 14 da intenção de registro de preço: 153079000812010"},"irp":{"href":"/licitacoes/id/irp/153079000812010","title":"Irp 153079000812010"},"material":{"href":"/materiais/id/material/20680","title":"Material 20680: null"},"modalidade_licitacao":{"href":"/licitacoes/id/modalidade_licitacao/5","title":"Modalidade de Licitação 5: PREGÃO                                            "},"participantes":{"href":"/licitacoes/id/irp/153079000812010/itens/14/participantes","title":"Participantes do Item de IRP"},"uasg":{"href":"/licitacoes/id/uasg/153079","title":"UASG 153079: UNIVERSIDADE FEDERAL DO PARANA"}}},{"uasg":153079,"numero_irp":812010,"numero_item":15,"id_irp":"153079000812010","modalidade_licitacao_item":5,"criterio_julgamento":"Menor Valor","codigo_material":20680,"descricao_detalhada":"CADEIRA ESCRITÓRIO, NOME CADEIRA ESCRITORIO","tipo":"Material","unidade_fornecimento":"un                  ","valor_estimado":"46.3300","_links":{"self":{"href":"/licitacoes/id/irp/153079000812010/itens/15","title":"Item 15 da intenção de registro de preço: 153079000812010"},"irp":{"href":"/licitacoes/id/irp/153079000812010","title":"Irp 153079000812010"},"material":{"href":"/materiais/id/material/20680","title":"Material 20680: null"},"modalidade_licitacao":{"href":"/licitacoes/id/modalidade_licitacao/5","title":"Modalidade de Licitação 5: PREGÃO                                            "},"participantes":{"href":"/licitacoes/id/irp/153079000812010/itens/15/participantes","title":"Participantes do Item de IRP"},"uasg":{"href":"/licitacoes/id/uasg/153079","title":"UASG 153079: UNIVERSIDADE FEDERAL DO PARANA"}}},{"uasg":153079,"numero_irp":812010,"numero_item":16,"id_irp":"153079000812010","modalidade_licitacao_item":5,"criterio_julgamento":"Menor Valor","codigo_material":20680,"descricao_detalhada":"CADEIRA ESCRITÓRIO, NOME CADEIRA ESCRITORIO","tipo":"Material","unidade_fornecimento":"un                  ","valor_estimado":"259.3300","_links":{"self":{"href":"/licitacoes/id/irp/153079000812010/itens/16","title":"Item 16 da intenção de registro de preço: 153079000812010"},"irp":{"href":"/licitacoes/id/irp/153079000812010","title":"Irp 153079000812010"},"material":{"href":"/materiais/id/material/20680","title":"Material 20680: null"},"modalidade_licitacao":{"href":"/licitacoes/id/modalidade_licitacao/5","title":"Modalidade de Licitação 5: PREGÃO                                            "},"participantes":{"href":"/licitacoes/id/irp/153079000812010/itens/16/participantes","title":"Participantes do Item de IRP"},"uasg":{"href":"/licitacoes/id/uasg/153079","title":"UASG 153079: UNIVERSIDADE FEDERAL DO PARANA"}}},{"uasg":153079,"numero_irp":812010,"numero_item":17,"id_irp":"153079000812010","modalidade_licitacao_item":5,"criterio_julgamento":"Menor Valor","codigo_material":20680,"descricao_detalhada":"CADEIRA ESCRITÓRIO, NOME CADEIRA ESCRITORIO","tipo":"Material","unidade_fornecimento":"un                  ","valor_estimado":"529.7400","_links":{"self":{"href":"/licitacoes/id/irp/153079000812010/itens/17","title":"Item 17 da intenção de registro de preço: 153079000812010"},"irp":{"href":"/licitacoes/id/irp/153079000812010","title":"Irp 153079000812010"},"material":{"href":"/materiais/id/material/20680","title":"Material 20680: null"},"modalidade_licitacao":{"href":"/licitacoes/id/modalidade_licitacao/5","title":"Modalidade de Licitação 5: PREGÃO                                            "},"participantes":{"href":"/licitacoes/id/irp/153079000812010/itens/17/participantes","title":"Participantes do Item de IRP"},"uasg":{"href":"/licitacoes/id/uasg/153079","title":"UASG 153079: UNIVERSIDADE FEDERAL DO PARANA"}}},{"uasg":153079,"numero_irp":812010,"numero_item":18,"id_irp":"153079000812010","modalidade_licitacao_item":5,"criterio_julgamento":"Menor Valor","codigo_material":20680,"descricao_detalhada":"CADEIRA ESCRITÓRIO, NOME CADEIRA ESCRITORIO","tipo":"Material","unidade_fornecimento":"un                  ","valor_estimado":"750.6500","_links":{"self":{"href":"/licitacoes/id/irp/153079000812010/itens/18","title":"Item 18 da intenção de registro de preço: 153079000812010"},"irp":{"href":"/licitacoes/id/irp/153079000812010","title":"Irp 153079000812010"},"material":{"href":"/materiais/id/material/20680","title":"Material 20680: null"},"modalidade_licitacao":{"href":"/licitacoes/id/modalidade_licitacao/5","title":"Modalidade de Licitação 5: PREGÃO                                            "},"participantes":{"href":"/licitacoes/id/irp/153079000812010/itens/18/participantes","title":"Participantes do Item de IRP"},"uasg":{"href":"/licitacoes/id/uasg/153079","title":"UASG 153079: UNIVERSIDADE FEDERAL DO PARANA"}}},{"uasg":153079,"numero_irp":812010,"numero_item":19,"id_irp":"153079000812010","modalidade_licitacao_item":5,"criterio_julgamento":"Menor Valor","codigo_material":20680,"descricao_detalhada":"CADEIRA ESCRITÓRIO, NOME CADEIRA ESCRITORIO","tipo":"Material","unidade_fornecimento":"un                  ","valor_estimado":"173.2300","_links":{"self":{"href":"/licitacoes/id/irp/153079000812010/itens/19","title":"Item 19 da intenção de registro de preço: 153079000812010"},"irp":{"href":"/licitacoes/id/irp/153079000812010","title":"Irp 153079000812010"},"material":{"href":"/materiais/id/material/20680","title":"Material 20680: null"},"modalidade_licitacao":{"href":"/licitacoes/id/modalidade_licitacao/5","title":"Modalidade de Licitação 5: PREGÃO                                            "},"participantes":{"href":"/licitacoes/id/irp/153079000812010/itens/19/participantes","title":"Participantes do Item de IRP"},"uasg":{"href":"/licitacoes/id/uasg/153079","title":"UASG 153079: UNIVERSIDADE FEDERAL DO PARANA"}}},{"uasg":153079,"numero_irp":812010,"numero_item":20,"id_irp":"153079000812010","modalidade_licitacao_item":5,"criterio_julgamento":"Menor Valor","codigo_material":20680,"descricao_detalhada":"CADEIRA ESCRITÓRIO, NOME CADEIRA ESCRITORIO","tipo":"Material","unidade_fornecimento":"un                  ","valor_estimado":"432.3000","_links":{"self":{"href":"/licitacoes/id/irp/153079000812010/itens/20","title":"Item 20 da intenção de registro de preço: 153079000812010"},"irp":{"href":"/licitacoes/id/irp/153079000812010","title":"Irp 153079000812010"},"material":{"href":"/materiais/id/material/20680","title":"Material 20680: null"},"modalidade_licitacao":{"href":"/licitacoes/id/modalidade_licitacao/5","title":"Modalidade de Licitação 5: PREGÃO                                            "},"participantes":{"href":"/licitacoes/id/irp/153079000812010/itens/20/participantes","title":"Participantes do Item de IRP"},"uasg":{"href":"/licitacoes/id/uasg/153079","title":"UASG 153079: UNIVERSIDADE FEDERAL DO PARANA"}}},{"uasg":153079,"numero_irp":812010,"numero_item":21,"id_irp":"153079000812010","modalidade_licitacao_item":5,"criterio_julgamento":"Menor Valor","codigo_material":20680,"descricao_detalhada":"CADEIRA ESCRITÓRIO, NOME CADEIRA ESCRITORIO","tipo":"Material","unidade_fornecimento":"un                  ","valor_estimado":"433.6700","_links":{"self":{"href":"/licitacoes/id/irp/153079000812010/itens/21","title":"Item 21 da intenção de registro de preço: 153079000812010"},"irp":{"href":"/licitacoes/id/irp/153079000812010","title":"Irp 153079000812010"},"material":{"href":"/materiais/id/material/20680","title":"Material 20680: null"},"modalidade_licitacao":{"href":"/licitacoes/id/modalidade_licitacao/5","title":"Modalidade de Licitação 5: PREGÃO                                            "},"participantes":{"href":"/licitacoes/id/irp/153079000812010/itens/21/participantes","title":"Participantes do Item de IRP"},"uasg":{"href":"/licitacoes/id/uasg/153079","title":"UASG 153079: UNIVERSIDADE FEDERAL DO PARANA"}}},{"uasg":153079,"numero_irp":812010,"numero_item":22,"id_irp":"153079000812010","modalidade_licitacao_item":5,"criterio_julgamento":"Menor Valor","codigo_material":20680,"descricao_detalhada":"CADEIRA ESCRITÓRIO, NOME CADEIRA ESCRITORIO","tipo":"Material","unidade_fornecimento":"un                  ","valor_estimado":"339.0000","_links":{"self":{"href":"/licitacoes/id/irp/153079000812010/itens/22","title":"Item 22 da intenção de registro de preço: 153079000812010"},"irp":{"href":"/licitacoes/id/irp/153079000812010","title":"Irp 153079000812010"},"material":{"href":"/materiais/id/material/20680","title":"Material 20680: null"},"modalidade_licitacao":{"href":"/licitacoes/id/modalidade_licitacao/5","title":"Modalidade de Licitação 5: PREGÃO                                            "},"participantes":{"href":"/licitacoes/id/irp/153079000812010/itens/22/participantes","title":"Participantes do Item de IRP"},"uasg":{"href":"/licitacoes/id/uasg/153079","title":"UASG 153079: UNIVERSIDADE FEDERAL DO PARANA"}}},{"uasg":153079,"numero_irp":812010,"numero_item":23,"id_irp":"153079000812010","modalidade_licitacao_item":5,"criterio_julgamento":"Menor Valor","codigo_material":20680,"descricao_detalhada":"CADEIRA ESCRITÓRIO, NOME CADEIRA ESCRITORIO","tipo":"Material","unidade_fornecimento":"un                  ","valor_estimado":"65.6000","_links":{"self":{"href":"/licitacoes/id/irp/153079000812010/itens/23","title":"Item 23 da intenção de registro de preço: 153079000812010"},"irp":{"href":"/licitacoes/id/irp/153079000812010","title":"Irp 153079000812010"},"material":{"href":"/materiais/id/material/20680","title":"Material 20680: null"},"modalidade_licitacao":{"href":"/licitacoes/id/modalidade_licitacao/5","title":"Modalidade de Licitação 5: PREGÃO                                            "},"participantes":{"href":"/licitacoes/id/irp/153079000812010/itens/23/participantes","title":"Participantes do Item de IRP"},"uasg":{"href":"/licitacoes/id/uasg/153079","title":"UASG 153079: UNIVERSIDADE FEDERAL DO PARANA"}}},{"uasg":153079,"numero_irp":812010,"numero_item":24,"id_irp":"153079000812010","modalidade_licitacao_item":5,"criterio_julgamento":"Menor Valor","codigo_material":26441,"descricao_detalhada":"CARTEIRA ESCOLAR, NOME CARTEIRA ESCOLAR","tipo":"Material","unidade_fornecimento":"un                  ","valor_estimado":"59.2700","_links":{"self":{"href":"/licitacoes/id/irp/153079000812010/itens/24","title":"Item 24 da intenção de registro de preço: 153079000812010"},"irp":{"href":"/licitacoes/id/irp/153079000812010","title":"Irp 153079000812010"},"material":{"href":"/materiais/id/material/26441","title":"Material 26441: null"},"modalidade_licitacao":{"href":"/licitacoes/id/modalidade_licitacao/5","title":"Modalidade de Licitação 5: PREGÃO                                            "},"participantes":{"href":"/licitacoes/id/irp/153079000812010/itens/24/participantes","title":"Participantes do Item de IRP"},"uasg":{"href":"/licitacoes/id/uasg/153079","title":"UASG 153079: UNIVERSIDADE FEDERAL DO PARANA"}}},{"uasg":153079,"numero_irp":812010,"numero_item":25,"id_irp":"153079000812010","modalidade_licitacao_item":5,"criterio_julgamento":"Menor Valor","codigo_material":150158,"descricao_detalhada":"ESCADA, NOME ESCADA","tipo":"Material","unidade_fornecimento":"un                  ","valor_estimado":"71.9700","_links":{"self":{"href":"/licitacoes/id/irp/153079000812010/itens/25","title":"Item 25 da intenção de registro de preço: 153079000812010"},"irp":{"href":"/licitacoes/id/irp/153079000812010","title":"Irp 153079000812010"},"material":{"href":"/materiais/id/material/150158","title":"Material 150158: null"},"modalidade_licitacao":{"href":"/licitacoes/id/modalidade_licitacao/5","title":"Modalidade de Licitação 5: PREGÃO                                            "},"participantes":{"href":"/licitacoes/id/irp/153079000812010/itens/25/participantes","title":"Participantes do Item de IRP"},"uasg":{"href":"/licitacoes/id/uasg/153079","title":"UASG 153079: UNIVERSIDADE FEDERAL DO PARANA"}}},{"uasg":153079,"numero_irp":812010,"numero_item":26,"id_irp":"153079000812010","modalidade_licitacao_item":5,"criterio_julgamento":"Menor Valor","codigo_material":150158,"descricao_detalhada":"ESCADA, NOME ESCADA","tipo":"Material","unidade_fornecimento":"un                  ","valor_estimado":"105.9700","_links":{"self":{"href":"/licitacoes/id/irp/153079000812010/itens/26","title":"Item 26 da intenção de registro de preço: 153079000812010"},"irp":{"href":"/licitacoes/id/irp/153079000812010","title":"Irp 153079000812010"},"material":{"href":"/materiais/id/material/150158","title":"Material 150158: null"},"modalidade_licitacao":{"href":"/licitacoes/id/modalidade_licitacao/5","title":"Modalidade de Licitação 5: PREGÃO                                            "},"participantes":{"href":"/licitacoes/id/irp/153079000812010/itens/26/participantes","title":"Participantes do Item de IRP"},"uasg":{"href":"/licitacoes/id/uasg/153079","title":"UASG 153079: UNIVERSIDADE FEDERAL DO PARANA"}}},{"uasg":153079,"numero_irp":812010,"numero_item":27,"id_irp":"153079000812010","modalidade_licitacao_item":5,"criterio_julgamento":"Menor Valor","codigo_material":150158,"descricao_detalhada":"ESCADA, NOME ESCADA","tipo":"Material","unidade_fornecimento":"un                  ","valor_estimado":"120.3000","_links":{"self":{"href":"/licitacoes/id/irp/153079000812010/itens/27","title":"Item 27 da intenção de registro de preço: 153079000812010"},"irp":{"href":"/licitacoes/id/irp/153079000812010","title":"Irp 153079000812010"},"material":{"href":"/materiais/id/material/150158","title":"Material 150158: null"},"modalidade_licitacao":{"href":"/licitacoes/id/modalidade_licitacao/5","title":"Modalidade de Licitação 5: PREGÃO                                            "},"participantes":{"href":"/licitacoes/id/irp/153079000812010/itens/27/participantes","title":"Participantes do Item de IRP"},"uasg":{"href":"/licitacoes/id/uasg/153079","title":"UASG 153079: UNIVERSIDADE FEDERAL DO PARANA"}}},{"uasg":153079,"numero_irp":812010,"numero_item":28,"id_irp":"153079000812010","modalidade_licitacao_item":5,"criterio_julgamento":"Menor Valor","codigo_material":150158,"descricao_detalhada":"ESCADA, NOME ESCADA","tipo":"Material","unidade_fornecimento":"un                  ","valor_estimado":"139.1700","_links":{"self":{"href":"/licitacoes/id/irp/153079000812010/itens/28","title":"Item 28 da intenção de registro de preço: 153079000812010"},"irp":{"href":"/licitacoes/id/irp/153079000812010","title":"Irp 153079000812010"},"material":{"href":"/materiais/id/material/150158","title":"Material 150158: null"},"modalidade_licitacao":{"href":"/licitacoes/id/modalidade_licitacao/5","title":"Modalidade de Licitação 5: PREGÃO                                            "},"participantes":{"href":"/licitacoes/id/irp/153079000812010/itens/28/participantes","title":"Participantes do Item de IRP"},"uasg":{"href":"/licitacoes/id/uasg/153079","title":"UASG 153079: UNIVERSIDADE FEDERAL DO PARANA"}}},{"uasg":153079,"numero_irp":812010,"numero_item":29,"id_irp":"153079000812010","modalidade_licitacao_item":5,"criterio_julgamento":"Menor Valor","codigo_material":150508,"descricao_detalhada":"ESTANTE, NOME ESTANTE","tipo":"Material","unidade_fornecimento":"un                  ","valor_estimado":"115.0000","_links":{"self":{"href":"/licitacoes/id/irp/153079000812010/itens/29","title":"Item 29 da intenção de registro de preço: 153079000812010"},"irp":{"href":"/licitacoes/id/irp/153079000812010","title":"Irp 153079000812010"},"material":{"href":"/materiais/id/material/150508","title":"Material 150508: null"},"modalidade_licitacao":{"href":"/licitacoes/id/modalidade_licitacao/5","title":"Modalidade de Licitação 5: PREGÃO                                            "},"participantes":{"href":"/licitacoes/id/irp/153079000812010/itens/29/participantes","title":"Participantes do Item de IRP"},"uasg":{"href":"/licitacoes/id/uasg/153079","title":"UASG 153079: UNIVERSIDADE FEDERAL DO PARANA"}}},{"uasg":153079,"numero_irp":812010,"numero_item":30,"id_irp":"153079000812010","modalidade_licitacao_item":5,"criterio_julgamento":"Menor Valor","codigo_material":150508,"descricao_detalhada":"ESTANTE, NOME ESTANTE","tipo":"Material","unidade_fornecimento":"un                  ","valor_estimado":"853.0100","_links":{"self":{"href":"/licitacoes/id/irp/153079000812010/itens/30","title":"Item 30 da intenção de registro de preço: 153079000812010"},"irp":{"href":"/licitacoes/id/irp/153079000812010","title":"Irp 153079000812010"},"material":{"href":"/materiais/id/material/150508","title":"Material 150508: null"},"modalidade_licitacao":{"href":"/licitacoes/id/modalidade_licitacao/5","title":"Modalidade de Licitação 5: PREGÃO                                            "},"participantes":{"href":"/licitacoes/id/irp/153079000812010/itens/30/participantes","title":"Participantes do Item de IRP"},"uasg":{"href":"/licitacoes/id/uasg/153079","title":"UASG 153079: UNIVERSIDADE FEDERAL DO PARANA"}}},{"uasg":153079,"numero_irp":812010,"numero_item":31,"id_irp":"153079000812010","modalidade_licitacao_item":5,"criterio_julgamento":"Menor Valor","codigo_material":150508,"descricao_detalhada":"ESTANTE, NOME ESTANTE","tipo":"Material","unidade_fornecimento":"un                  ","valor_estimado":"248.3300","_links":{"self":{"href":"/licitacoes/id/irp/153079000812010/itens/31","title":"Item 31 da intenção de registro de preço: 153079000812010"},"irp":{"href":"/licitacoes/id/irp/153079000812010","title":"Irp 153079000812010"},"material":{"href":"/materiais/id/material/150508","title":"Material 150508: null"},"modalidade_licitacao":{"href":"/licitacoes/id/modalidade_licitacao/5","title":"Modalidade de Licitação 5: PREGÃO                                            "},"participantes":{"href":"/licitacoes/id/irp/153079000812010/itens/31/participantes","title":"Participantes do Item de IRP"},"uasg":{"href":"/licitacoes/id/uasg/153079","title":"UASG 153079: UNIVERSIDADE FEDERAL DO PARANA"}}},{"uasg":153079,"numero_irp":812010,"numero_item":32,"id_irp":"153079000812010","modalidade_licitacao_item":5,"criterio_julgamento":"Menor Valor","codigo_material":70173,"descricao_detalhada":"GAVETEIRO MÓVEL, NOME GAVETEIRO","tipo":"Material","unidade_fornecimento":"un                  ","valor_estimado":"360.6700","_links":{"self":{"href":"/licitacoes/id/irp/153079000812010/itens/32","title":"Item 32 da intenção de registro de preço: 153079000812010"},"irp":{"href":"/licitacoes/id/irp/153079000812010","title":"Irp 153079000812010"},"material":{"href":"/materiais/id/material/70173","title":"Material 70173: null"},"modalidade_licitacao":{"href":"/licitacoes/id/modalidade_licitacao/5","title":"Modalidade de Licitação 5: PREGÃO                                            "},"participantes":{"href":"/licitacoes/id/irp/153079000812010/itens/32/participantes","title":"Participantes do Item de IRP"},"uasg":{"href":"/licitacoes/id/uasg/153079","title":"UASG 153079: UNIVERSIDADE FEDERAL DO PARANA"}}},{"uasg":153079,"numero_irp":812010,"numero_item":33,"id_irp":"153079000812010","modalidade_licitacao_item":5,"criterio_julgamento":"Menor Valor","codigo_material":70173,"descricao_detalhada":"GAVETEIRO MÓVEL, NOME GAVETEIRO","tipo":"Material","unidade_fornecimento":"un                  ","valor_estimado":"288.4700","_links":{"self":{"href":"/licitacoes/id/irp/153079000812010/itens/33","title":"Item 33 da intenção de registro de preço: 153079000812010"},"irp":{"href":"/licitacoes/id/irp/153079000812010","title":"Irp 153079000812010"},"material":{"href":"/materiais/id/material/70173","title":"Material 70173: null"},"modalidade_licitacao":{"href":"/licitacoes/id/modalidade_licitacao/5","title":"Modalidade de Licitação 5: PREGÃO                                            "},"participantes":{"href":"/licitacoes/id/irp/153079000812010/itens/33/participantes","title":"Participantes do Item de IRP"},"uasg":{"href":"/licitacoes/id/uasg/153079","title":"UASG 153079: UNIVERSIDADE FEDERAL DO PARANA"}}},{"uasg":153079,"numero_irp":812010,"numero_item":34,"id_irp":"153079000812010","modalidade_licitacao_item":5,"criterio_julgamento":"Menor Valor","codigo_material":73849,"descricao_detalhada":"MAPOTECA, NOME MAPOTECA","tipo":"Material","unidade_fornecimento":"un                  ","valor_estimado":"1776.6600","_links":{"self":{"href":"/licitacoes/id/irp/153079000812010/itens/34","title":"Item 34 da intenção de registro de preço: 153079000812010"},"irp":{"href":"/licitacoes/id/irp/153079000812010","title":"Irp 153079000812010"},"material":{"href":"/materiais/id/material/73849","title":"Material 73849: null"},"modalidade_licitacao":{"href":"/licitacoes/id/modalidade_licitacao/5","title":"Modalidade de Licitação 5: PREGÃO                                            "},"participantes":{"href":"/licitacoes/id/irp/153079000812010/itens/34/participantes","title":"Participantes do Item de IRP"},"uasg":{"href":"/licitacoes/id/uasg/153079","title":"UASG 153079: UNIVERSIDADE FEDERAL DO PARANA"}}},{"uasg":153079,"numero_irp":812010,"numero_item":35,"id_irp":"153079000812010","modalidade_licitacao_item":5,"criterio_julgamento":"Menor Valor","codigo_material":150056,"descricao_detalhada":"MESA ESCRITÓRIO, NOME MESA ESCRITÓRIO","tipo":"Material","unidade_fornecimento":"un                  ","valor_estimado":"224.9500","_links":{"self":{"href":"/licitacoes/id/irp/153079000812010/itens/35","title":"Item 35 da intenção de registro de preço: 153079000812010"},"irp":{"href":"/licitacoes/id/irp/153079000812010","title":"Irp 153079000812010"},"material":{"href":"/materiais/id/material/150056","title":"Material 150056: null"},"modalidade_licitacao":{"href":"/licitacoes/id/modalidade_licitacao/5","title":"Modalidade de Licitação 5: PREGÃO                                            "},"participantes":{"href":"/licitacoes/id/irp/153079000812010/itens/35/participantes","title":"Participantes do Item de IRP"},"uasg":{"href":"/licitacoes/id/uasg/153079","title":"UASG 153079: UNIVERSIDADE FEDERAL DO PARANA"}}},{"uasg":153079,"numero_irp":812010,"numero_item":36,"id_irp":"153079000812010","modalidade_licitacao_item":5,"criterio_julgamento":"Menor Valor","codigo_material":150056,"descricao_detalhada":"MESA ESCRITÓRIO, NOME MESA ESCRITÓRIO","tipo":"Material","unidade_fornecimento":"un                  ","valor_estimado":"268.3300","_links":{"self":{"href":"/licitacoes/id/irp/153079000812010/itens/36","title":"Item 36 da intenção de registro de preço: 153079000812010"},"irp":{"href":"/licitacoes/id/irp/153079000812010","title":"Irp 153079000812010"},"material":{"href":"/materiais/id/material/150056","title":"Material 150056: null"},"modalidade_licitacao":{"href":"/licitacoes/id/modalidade_licitacao/5","title":"Modalidade de Licitação 5: PREGÃO                                            "},"participantes":{"href":"/licitacoes/id/irp/153079000812010/itens/36/participantes","title":"Participantes do Item de IRP"},"uasg":{"href":"/licitacoes/id/uasg/153079","title":"UASG 153079: UNIVERSIDADE FEDERAL DO PARANA"}}},{"uasg":153079,"numero_irp":812010,"numero_item":37,"id_irp":"153079000812010","modalidade_licitacao_item":5,"criterio_julgamento":"Menor Valor","codigo_material":150056,"descricao_detalhada":"MESA ESCRITÓRIO, NOME MESA ESCRITÓRIO","tipo":"Material","unidade_fornecimento":"un                  ","valor_estimado":"430.7600","_links":{"self":{"href":"/licitacoes/id/irp/153079000812010/itens/37","title":"Item 37 da intenção de registro de preço: 153079000812010"},"irp":{"href":"/licitacoes/id/irp/153079000812010","title":"Irp 153079000812010"},"material":{"href":"/materiais/id/material/150056","title":"Material 150056: null"},"modalidade_licitacao":{"href":"/licitacoes/id/modalidade_licitacao/5","title":"Modalidade de Licitação 5: PREGÃO                                            "},"participantes":{"href":"/licitacoes/id/irp/153079000812010/itens/37/participantes","title":"Participantes do Item de IRP"},"uasg":{"href":"/licitacoes/id/uasg/153079","title":"UASG 153079: UNIVERSIDADE FEDERAL DO PARANA"}}},{"uasg":153079,"numero_irp":812010,"numero_item":38,"id_irp":"153079000812010","modalidade_licitacao_item":5,"criterio_julgamento":"Menor Valor","codigo_material":150056,"descricao_detalhada":"MESA ESCRITÓRIO, NOME MESA ESCRITÓRIO","tipo":"Material","unidade_fornecimento":"un                  ","valor_estimado":"514.6700","_links":{"self":{"href":"/licitacoes/id/irp/153079000812010/itens/38","title":"Item 38 da intenção de registro de preço: 153079000812010"},"irp":{"href":"/licitacoes/id/irp/153079000812010","title":"Irp 153079000812010"},"material":{"href":"/materiais/id/material/150056","title":"Material 150056: null"},"modalidade_licitacao":{"href":"/licitacoes/id/modalidade_licitacao/5","title":"Modalidade de Licitação 5: PREGÃO                                            "},"participantes":{"href":"/licitacoes/id/irp/153079000812010/itens/38/participantes","title":"Participantes do Item de IRP"},"uasg":{"href":"/licitacoes/id/uasg/153079","title":"UASG 153079: UNIVERSIDADE FEDERAL DO PARANA"}}},{"uasg":153079,"numero_irp":812010,"numero_item":39,"id_irp":"153079000812010","modalidade_licitacao_item":5,"criterio_julgamento":"Menor Valor","codigo_material":150056,"descricao_detalhada":"MESA ESCRITÓRIO, NOME MESA ESCRITÓRIO","tipo":"Material","unidade_fornecimento":"un                  ","valor_estimado":"272.6700","_links":{"self":{"href":"/licitacoes/id/irp/153079000812010/itens/39","title":"Item 39 da intenção de registro de preço: 153079000812010"},"irp":{"href":"/licitacoes/id/irp/153079000812010","title":"Irp 153079000812010"},"material":{"href":"/materiais/id/material/150056","title":"Material 150056: null"},"modalidade_licitacao":{"href":"/licitacoes/id/modalidade_licitacao/5","title":"Modalidade de Licitação 5: PREGÃO                                            "},"participantes":{"href":"/licitacoes/id/irp/153079000812010/itens/39/participantes","title":"Participantes do Item de IRP"},"uasg":{"href":"/licitacoes/id/uasg/153079","title":"UASG 153079: UNIVERSIDADE FEDERAL DO PARANA"}}},{"uasg":153079,"numero_irp":812010,"numero_item":40,"id_irp":"153079000812010","modalidade_licitacao_item":5,"criterio_julgamento":"Menor Valor","codigo_material":150056,"descricao_detalhada":"MESA ESCRITÓRIO, NOME MESA ESCRITÓRIO","tipo":"Material","unidade_fornecimento":"un                  ","valor_estimado":"875.0000","_links":{"self":{"href":"/licitacoes/id/irp/153079000812010/itens/40","title":"Item 40 da intenção de registro de preço: 153079000812010"},"irp":{"href":"/licitacoes/id/irp/153079000812010","title":"Irp 153079000812010"},"material":{"href":"/materiais/id/material/150056","title":"Material 150056: null"},"modalidade_licitacao":{"href":"/licitacoes/id/modalidade_licitacao/5","title":"Modalidade de Licitação 5: PREGÃO                                            "},"participantes":{"href":"/licitacoes/id/irp/153079000812010/itens/40/participantes","title":"Participantes do Item de IRP"},"uasg":{"href":"/licitacoes/id/uasg/153079","title":"UASG 153079: UNIVERSIDADE FEDERAL DO PARANA"}}},{"uasg":153079,"numero_irp":812010,"numero_item":41,"id_irp":"153079000812010","modalidade_licitacao_item":5,"criterio_julgamento":"Menor Valor","codigo_material":150056,"descricao_detalhada":"MESA ESCRITÓRIO, NOME MESA ESCRITÓRIO","tipo":"Material","unidade_fornecimento":"un                  ","valor_estimado":"429.7000","_links":{"self":{"href":"/licitacoes/id/irp/153079000812010/itens/41","title":"Item 41 da intenção de registro de preço: 153079000812010"},"irp":{"href":"/licitacoes/id/irp/153079000812010","title":"Irp 153079000812010"},"material":{"href":"/materiais/id/material/150056","title":"Material 150056: null"},"modalidade_licitacao":{"href":"/licitacoes/id/modalidade_licitacao/5","title":"Modalidade de Licitação 5: PREGÃO                                            "},"participantes":{"href":"/licitacoes/id/irp/153079000812010/itens/41/participantes","title":"Participantes do Item de IRP"},"uasg":{"href":"/licitacoes/id/uasg/153079","title":"UASG 153079: UNIVERSIDADE FEDERAL DO PARANA"}}},{"uasg":153079,"numero_irp":812010,"numero_item":42,"id_irp":"153079000812010","modalidade_licitacao_item":5,"criterio_julgamento":"Menor Valor","codigo_material":150056,"descricao_detalhada":"MESA ESCRITÓRIO, NOME MESA ESCRITÓRIO","tipo":"Material","unidade_fornecimento":"un                  ","valor_estimado":"433.6600","_links":{"self":{"href":"/licitacoes/id/irp/153079000812010/itens/42","title":"Item 42 da intenção de registro de preço: 153079000812010"},"irp":{"href":"/licitacoes/id/irp/153079000812010","title":"Irp 153079000812010"},"material":{"href":"/materiais/id/material/150056","title":"Material 150056: null"},"modalidade_licitacao":{"href":"/licitacoes/id/modalidade_licitacao/5","title":"Modalidade de Licitação 5: PREGÃO                                            "},"participantes":{"href":"/licitacoes/id/irp/153079000812010/itens/42/participantes","title":"Participantes do Item de IRP"},"uasg":{"href":"/licitacoes/id/uasg/153079","title":"UASG 153079: UNIVERSIDADE FEDERAL DO PARANA"}}},{"uasg":153079,"numero_irp":812010,"numero_item":43,"id_irp":"153079000812010","modalidade_licitacao_item":5,"criterio_julgamento":"Menor Valor","codigo_material":150056,"descricao_detalhada":"MESA ESCRITÓRIO, NOME MESA ESCRITÓRIO","tipo":"Material","unidade_fornecimento":"un                  ","valor_estimado":"456.6300","_links":{"self":{"href":"/licitacoes/id/irp/153079000812010/itens/43","title":"Item 43 da intenção de registro de preço: 153079000812010"},"irp":{"href":"/licitacoes/id/irp/153079000812010","title":"Irp 153079000812010"},"material":{"href":"/materiais/id/material/150056","title":"Material 150056: null"},"modalidade_licitacao":{"href":"/licitacoes/id/modalidade_licitacao/5","title":"Modalidade de Licitação 5: PREGÃO                                            "},"participantes":{"href":"/licitacoes/id/irp/153079000812010/itens/43/participantes","title":"Participantes do Item de IRP"},"uasg":{"href":"/licitacoes/id/uasg/153079","title":"UASG 153079: UNIVERSIDADE FEDERAL DO PARANA"}}},{"uasg":153079,"numero_irp":812010,"numero_item":44,"id_irp":"153079000812010","modalidade_licitacao_item":5,"criterio_julgamento":"Menor Valor","codigo_material":150786,"descricao_detalhada":"MESA ESCOLAR, NOME MESA ESCOLAR","tipo":"Material","unidade_fornecimento":"un                  ","valor_estimado":"158.6200","_links":{"self":{"href":"/licitacoes/id/irp/153079000812010/itens/44","title":"Item 44 da intenção de registro de preço: 153079000812010"},"irp":{"href":"/licitacoes/id/irp/153079000812010","title":"Irp 153079000812010"},"material":{"href":"/materiais/id/material/150786","title":"Material 150786: null"},"modalidade_licitacao":{"href":"/licitacoes/id/modalidade_licitacao/5","title":"Modalidade de Licitação 5: PREGÃO                                            "},"participantes":{"href":"/licitacoes/id/irp/153079000812010/itens/44/participantes","title":"Participantes do Item de IRP"},"uasg":{"href":"/licitacoes/id/uasg/153079","title":"UASG 153079: UNIVERSIDADE FEDERAL DO PARANA"}}},{"uasg":153079,"numero_irp":812010,"numero_item":45,"id_irp":"153079000812010","modalidade_licitacao_item":5,"criterio_julgamento":"Menor Valor","codigo_material":150786,"descricao_detalhada":"MESA ESCOLAR, NOME MESA ESCOLAR","tipo":"Material","unidade_fornecimento":"un                  ","valor_estimado":"201.6700","_links":{"self":{"href":"/licitacoes/id/irp/153079000812010/itens/45","title":"Item 45 da intenção de registro de preço: 153079000812010"},"irp":{"href":"/licitacoes/id/irp/153079000812010","title":"Irp 153079000812010"},"material":{"href":"/materiais/id/material/150786","title":"Material 150786: null"},"modalidade_licitacao":{"href":"/licitacoes/id/modalidade_licitacao/5","title":"Modalidade de Licitação 5: PREGÃO                                            "},"participantes":{"href":"/licitacoes/id/irp/153079000812010/itens/45/participantes","title":"Participantes do Item de IRP"},"uasg":{"href":"/licitacoes/id/uasg/153079","title":"UASG 153079: UNIVERSIDADE FEDERAL DO PARANA"}}},{"uasg":153079,"numero_irp":812010,"numero_item":46,"id_irp":"153079000812010","modalidade_licitacao_item":5,"criterio_julgamento":"Menor Valor","codigo_material":150290,"descricao_detalhada":"MESA DE DESENHO, NOME MESA DE DESENHO","tipo":"Material","unidade_fornecimento":"un                  ","valor_estimado":"560.3300","_links":{"self":{"href":"/licitacoes/id/irp/153079000812010/itens/46","title":"Item 46 da intenção de registro de preço: 153079000812010"},"irp":{"href":"/licitacoes/id/irp/153079000812010","title":"Irp 153079000812010"},"material":{"href":"/materiais/id/material/150290","title":"Material 150290: null"},"modalidade_licitacao":{"href":"/licitacoes/id/modalidade_licitacao/5","title":"Modalidade de Licitação 5: PREGÃO                                            "},"participantes":{"href":"/licitacoes/id/irp/153079000812010/itens/46/participantes","title":"Participantes do Item de IRP"},"uasg":{"href":"/licitacoes/id/uasg/153079","title":"UASG 153079: UNIVERSIDADE FEDERAL DO PARANA"}}},{"uasg":153079,"numero_irp":812010,"numero_item":47,"id_irp":"153079000812010","modalidade_licitacao_item":5,"criterio_julgamento":"Menor Valor","codigo_material":150056,"descricao_detalhada":"MESA ESCRITÓRIO, NOME MESA ESCRITÓRIO","tipo":"Material","unidade_fornecimento":"un                  ","valor_estimado":"1065.3300","_links":{"self":{"href":"/licitacoes/id/irp/153079000812010/itens/47","title":"Item 47 da intenção de registro de preço: 153079000812010"},"irp":{"href":"/licitacoes/id/irp/153079000812010","title":"Irp 153079000812010"},"material":{"href":"/materiais/id/material/150056","title":"Material 150056: null"},"modalidade_licitacao":{"href":"/licitacoes/id/modalidade_licitacao/5","title":"Modalidade de Licitação 5: PREGÃO                                            "},"participantes":{"href":"/licitacoes/id/irp/153079000812010/itens/47/participantes","title":"Participantes do Item de IRP"},"uasg":{"href":"/licitacoes/id/uasg/153079","title":"UASG 153079: UNIVERSIDADE FEDERAL DO PARANA"}}},{"uasg":153079,"numero_irp":812010,"numero_item":48,"id_irp":"153079000812010","modalidade_licitacao_item":5,"criterio_julgamento":"Menor Valor","codigo_material":14320,"descricao_detalhada":"POLTRONA, NOME POLTRONA","tipo":"Material","unidade_fornecimento":"un                  ","valor_estimado":"345.3300","_links":{"self":{"href":"/licitacoes/id/irp/153079000812010/itens/48","title":"Item 48 da intenção de registro de preço: 153079000812010"},"irp":{"href":"/licitacoes/id/irp/153079000812010","title":"Irp 153079000812010"},"material":{"href":"/materiais/id/material/14320","title":"Material 14320: null"},"modalidade_licitacao":{"href":"/licitacoes/id/modalidade_licitacao/5","title":"Modalidade de Licitação 5: PREGÃO                                            "},"participantes":{"href":"/licitacoes/id/irp/153079000812010/itens/48/participantes","title":"Participantes do Item de IRP"},"uasg":{"href":"/licitacoes/id/uasg/153079","title":"UASG 153079: UNIVERSIDADE FEDERAL DO PARANA"}}},{"uasg":153079,"numero_irp":812010,"numero_item":49,"id_irp":"153079000812010","modalidade_licitacao_item":5,"criterio_julgamento":"Menor Valor","codigo_material":14320,"descricao_detalhada":"POLTRONA, NOME POLTRONA","tipo":"Material","unidade_fornecimento":"un                  ","valor_estimado":"862.0000","_links":{"self":{"href":"/licitacoes/id/irp/153079000812010/itens/49","title":"Item 49 da intenção de registro de preço: 153079000812010"},"irp":{"href":"/licitacoes/id/irp/153079000812010","title":"Irp 153079000812010"},"material":{"href":"/materiais/id/material/14320","title":"Material 14320: null"},"modalidade_licitacao":{"href":"/licitacoes/id/modalidade_licitacao/5","title":"Modalidade de Licitação 5: PREGÃO                                            "},"participantes":{"href":"/licitacoes/id/irp/153079000812010/itens/49/participantes","title":"Participantes do Item de IRP"},"uasg":{"href":"/licitacoes/id/uasg/153079","title":"UASG 153079: UNIVERSIDADE FEDERAL DO PARANA"}}},{"uasg":153079,"numero_irp":812010,"numero_item":50,"id_irp":"153079000812010","modalidade_licitacao_item":5,"criterio_julgamento":"Menor Valor","codigo_material":14320,"descricao_detalhada":"POLTRONA, NOME POLTRONA","tipo":"Material","unidade_fornecimento":"un                  ","valor_estimado":"706.3000","_links":{"self":{"href":"/licitacoes/id/irp/153079000812010/itens/50","title":"Item 50 da intenção de registro de preço: 153079000812010"},"irp":{"href":"/licitacoes/id/irp/153079000812010","title":"Irp 153079000812010"},"material":{"href":"/materiais/id/material/14320","title":"Material 14320: null"},"modalidade_licitacao":{"href":"/licitacoes/id/modalidade_licitacao/5","title":"Modalidade de Licitação 5: PREGÃO                                            "},"participantes":{"href":"/licitacoes/id/irp/153079000812010/itens/50/participantes","title":"Participantes do Item de IRP"},"uasg":{"href":"/licitacoes/id/uasg/153079","title":"UASG 153079: UNIVERSIDADE FEDERAL DO PARANA"}}},{"uasg":153079,"numero_irp":812010,"numero_item":51,"id_irp":"153079000812010","modalidade_licitacao_item":5,"criterio_julgamento":"Menor Valor","codigo_material":150153,"descricao_detalhada":"QUADRO AVISOS, NOME QUADRO AVISOS","tipo":"Material","unidade_fornecimento":"un                  ","valor_estimado":"56.8500","_links":{"self":{"href":"/licitacoes/id/irp/153079000812010/itens/51","title":"Item 51 da intenção de registro de preço: 153079000812010"},"irp":{"href":"/licitacoes/id/irp/153079000812010","title":"Irp 153079000812010"},"material":{"href":"/materiais/id/material/150153","title":"Material 150153: null"},"modalidade_licitacao":{"href":"/licitacoes/id/modalidade_licitacao/5","title":"Modalidade de Licitação 5: PREGÃO                                            "},"participantes":{"href":"/licitacoes/id/irp/153079000812010/itens/51/participantes","title":"Participantes do Item de IRP"},"uasg":{"href":"/licitacoes/id/uasg/153079","title":"UASG 153079: UNIVERSIDADE FEDERAL DO PARANA"}}},{"uasg":153079,"numero_irp":812010,"numero_item":52,"id_irp":"153079000812010","modalidade_licitacao_item":5,"criterio_julgamento":"Menor Valor","codigo_material":140805,"descricao_detalhada":"QUADRO BRANCO, NOME QUADRO BRANCO","tipo":"Material","unidade_fornecimento":"un                  ","valor_estimado":"154.5800","_links":{"self":{"href":"/licitacoes/id/irp/153079000812010/itens/52","title":"Item 52 da intenção de registro de preço: 153079000812010"},"irp":{"href":"/licitacoes/id/irp/153079000812010","title":"Irp 153079000812010"},"material":{"href":"/materiais/id/material/140805","title":"Material 140805: null"},"modalidade_licitacao":{"href":"/licitacoes/id/modalidade_licitacao/5","title":"Modalidade de Licitação 5: PREGÃO                                            "},"participantes":{"href":"/licitacoes/id/irp/153079000812010/itens/52/participantes","title":"Participantes do Item de IRP"},"uasg":{"href":"/licitacoes/id/uasg/153079","title":"UASG 153079: UNIVERSIDADE FEDERAL DO PARANA"}}},{"uasg":153079,"numero_irp":812010,"numero_item":53,"id_irp":"153079000812010","modalidade_licitacao_item":5,"criterio_julgamento":"Menor Valor","codigo_material":140805,"descricao_detalhada":"QUADRO BRANCO, NOME QUADRO BRANCO","tipo":"Material","unidade_fornecimento":"un                  ","valor_estimado":"151.6300","_links":{"self":{"href":"/licitacoes/id/irp/153079000812010/itens/53","title":"Item 53 da intenção de registro de preço: 153079000812010"},"irp":{"href":"/licitacoes/id/irp/153079000812010","title":"Irp 153079000812010"},"material":{"href":"/materiais/id/material/140805","title":"Material 140805: null"},"modalidade_licitacao":{"href":"/licitacoes/id/modalidade_licitacao/5","title":"Modalidade de Licitação 5: PREGÃO                                            "},"participantes":{"href":"/licitacoes/id/irp/153079000812010/itens/53/participantes","title":"Participantes do Item de IRP"},"uasg":{"href":"/licitacoes/id/uasg/153079","title":"UASG 153079: UNIVERSIDADE FEDERAL DO PARANA"}}},{"uasg":153079,"numero_irp":812010,"numero_item":54,"id_irp":"153079000812010","modalidade_licitacao_item":5,"criterio_julgamento":"Menor Valor","codigo_material":150836,"descricao_detalhada":"QUADRO, NOME QUADRO","tipo":"Material","unidade_fornecimento":"un                  ","valor_estimado":"432.3300","_links":{"self":{"href":"/licitacoes/id/irp/153079000812010/itens/54","title":"Item 54 da intenção de registro de preço: 153079000812010"},"irp":{"href":"/licitacoes/id/irp/153079000812010","title":"Irp 153079000812010"},"material":{"href":"/materiais/id/material/150836","title":"Material 150836: null"},"modalidade_licitacao":{"href":"/licitacoes/id/modalidade_licitacao/5","title":"Modalidade de Licitação 5: PREGÃO                                            "},"participantes":{"href":"/licitacoes/id/irp/153079000812010/itens/54/participantes","title":"Participantes do Item de IRP"},"uasg":{"href":"/licitacoes/id/uasg/153079","title":"UASG 153079: UNIVERSIDADE FEDERAL DO PARANA"}}},{"uasg":153079,"numero_irp":812010,"numero_item":55,"id_irp":"153079000812010","modalidade_licitacao_item":5,"criterio_julgamento":"Menor Valor","codigo_material":150836,"descricao_detalhada":"QUADRO, NOME QUADRO","tipo":"Material","unidade_fornecimento":"un                  ","valor_estimado":"646.6300","_links":{"self":{"href":"/licitacoes/id/irp/153079000812010/itens/55","title":"Item 55 da intenção de registro de preço: 153079000812010"},"irp":{"href":"/licitacoes/id/irp/153079000812010","title":"Irp 153079000812010"},"material":{"href":"/materiais/id/material/150836","title":"Material 150836: null"},"modalidade_licitacao":{"href":"/licitacoes/id/modalidade_licitacao/5","title":"Modalidade de Licitação 5: PREGÃO                                            "},"participantes":{"href":"/licitacoes/id/irp/153079000812010/itens/55/participantes","title":"Participantes do Item de IRP"},"uasg":{"href":"/licitacoes/id/uasg/153079","title":"UASG 153079: UNIVERSIDADE FEDERAL DO PARANA"}}},{"uasg":153079,"numero_irp":812010,"numero_item":56,"id_irp":"153079000812010","modalidade_licitacao_item":5,"criterio_julgamento":"Menor Valor","codigo_material":140805,"descricao_detalhada":"QUADRO BRANCO, NOME QUADRO BRANCO","tipo":"Material","unidade_fornecimento":"un                  ","valor_estimado":"408.6700","_links":{"self":{"href":"/licitacoes/id/irp/153079000812010/itens/56","title":"Item 56 da intenção de registro de preço: 153079000812010"},"irp":{"href":"/licitacoes/id/irp/153079000812010","title":"Irp 153079000812010"},"material":{"href":"/materiais/id/material/140805","title":"Material 140805: null"},"modalidade_licitacao":{"href":"/licitacoes/id/modalidade_licitacao/5","title":"Modalidade de Licitação 5: PREGÃO                                            "},"participantes":{"href":"/licitacoes/id/irp/153079000812010/itens/56/participantes","title":"Participantes do Item de IRP"},"uasg":{"href":"/licitacoes/id/uasg/153079","title":"UASG 153079: UNIVERSIDADE FEDERAL DO PARANA"}}},{"uasg":153079,"numero_irp":812010,"numero_item":57,"id_irp":"153079000812010","modalidade_licitacao_item":5,"criterio_julgamento":"Menor Valor","codigo_material":140805,"descricao_detalhada":"QUADRO BRANCO, NOME QUADRO BRANCO","tipo":"Material","unidade_fornecimento":"un                  ","valor_estimado":"243.7500","_links":{"self":{"href":"/licitacoes/id/irp/153079000812010/itens/57","title":"Item 57 da intenção de registro de preço: 153079000812010"},"irp":{"href":"/licitacoes/id/irp/153079000812010","title":"Irp 153079000812010"},"material":{"href":"/materiais/id/material/140805","title":"Material 140805: null"},"modalidade_licitacao":{"href":"/licitacoes/id/modalidade_licitacao/5","title":"Modalidade de Licitação 5: PREGÃO                                            "},"participantes":{"href":"/licitacoes/id/irp/153079000812010/itens/57/participantes","title":"Participantes do Item de IRP"},"uasg":{"href":"/licitacoes/id/uasg/153079","title":"UASG 153079: UNIVERSIDADE FEDERAL DO PARANA"}}},{"uasg":153079,"numero_irp":812010,"numero_item":58,"id_irp":"153079000812010","modalidade_licitacao_item":5,"criterio_julgamento":"Menor Valor","codigo_material":150465,"descricao_detalhada":"SUPORTE, NOME SUPORTE","tipo":"Material","unidade_fornecimento":"un                  ","valor_estimado":"110.0000","_links":{"self":{"href":"/licitacoes/id/irp/153079000812010/itens/58","title":"Item 58 da intenção de registro de preço: 153079000812010"},"irp":{"href":"/licitacoes/id/irp/153079000812010","title":"Irp 153079000812010"},"material":{"href":"/materiais/id/material/150465","title":"Material 150465: null"},"modalidade_licitacao":{"href":"/licitacoes/id/modalidade_licitacao/5","title":"Modalidade de Licitação 5: PREGÃO                                            "},"participantes":{"href":"/licitacoes/id/irp/153079000812010/itens/58/participantes","title":"Participantes do Item de IRP"},"uasg":{"href":"/licitacoes/id/uasg/153079","title":"UASG 153079: UNIVERSIDADE FEDERAL DO PARANA"}}}]},"count":58}