{"_links":{"self":{"href":"http://compras.dados.gov.br/licitacoes/doc/licitacao/15405505000292016/itens.json","title":"Lista de itens da licitação"},"first":{"href":"/licitacoes/doc/licitacao/15405505000292016/itens.json?offset=0","title":"Primeira página"}},"_embedded":{"itensLicitacao":[{"uasg":154055,"modalidade":5,"numero_aviso":292016,"numero_licitacao":"15405505000292016","numero_item_licitacao":1,"codigo_item_servico":507,"descricao_item":"Contratação de empresa especializada para a elaboração de Projetos para:Elabor ação de Projetos para climatização/ventilação do restaurante Universitário do campus de Porto Velho (RO);  Elaboração de Projetos para climatização/ventilaç ão do restaurante Universitário do campus de Ji-Paraná (RO);  Elaboração de Pr ojetos para climatização/ventilação do restaurante Universitário do campus de Cacoal (RO);  Elaboração de Projetos para climatização/ventilação do restauran te Universitário do campus de Rolim Moura (RO);","quantidade":"1","unidade":"Serviço","cnpj_fornecedor":"13384705000100","cpfVencedor":"","beneficio":"Nao possui tratamento diferenciado para ME/EPP/COOPERATIVA","valor_estimado":29200.00,"decreto_7174":false,"criterio_julgamento":"Menor Valor","_links":{"self":{"href":"/licitacoes/doc/licitacao/15405505000292016/itens/1","title":"Item 1 da licitação 15405505000292016"},"fornecedor":{"href":"/fornecedores/id/fornecedor_pj/13384705000100","title":"Fornecedor 13384705000100: CONSTRUTORA MAXXI LTDA - EPP"},"licitacao":{"href":"/licitacoes/id/licitacao/15405505000292016","title":"Licitação 15405505000292016"},"modalidade_licitacao":{"href":"/licitacoes/id/modalidade_licitacao/5","title":"Modalidade de Licitação 5: PREGÃO                                            "},"servico":{"href":"/servicos/id/servico/507","title":"Servico 507: ESTUDOS E PROJETOS DE SISTEMAS DE REFRIGERACAO                                                                          "},"uasg":{"href":"/licitacoes/id/uasg/154055","title":"UASG 154055: MEC-FUNDACAO UNIVERSIDADE DE RONDONIA/RO"}}}]},"count":1}