{"_links":{"self":{"href":"http://compras.dados.gov.br/licitacoes/doc/licitacao/15403205000082014/itens.json","title":"Lista de itens da licitação"},"first":{"href":"/licitacoes/doc/licitacao/15403205000082014/itens.json?offset=0","title":"Primeira página"}},"_embedded":{"itensLicitacao":[{"uasg":154032,"modalidade":5,"numero_aviso":82014,"numero_licitacao":"15403205000082014","numero_item_licitacao":1,"codigo_item_servico":94,"descricao_item":"Serviço especializado para realização de Estudo de Impacto de Tráfego em terre nos situados na Rua Corrêa Lima, 1239/1259/1381Bairro Santa TeresaPorto Alegre/RS, abrangendo área de aproximadamente 15.300 metros quadrados.","quantidade":"1","unidade":"SERVIÇO","cnpj_fornecedor":"02923857000109","cpfVencedor":"","beneficio":"Nao possui tratamento diferenciado para ME/EPP/COOPERATIVA","valor_estimado":35000.00,"decreto_7174":false,"criterio_julgamento":"Menor Valor","_links":{"self":{"href":"/licitacoes/doc/licitacao/15403205000082014/itens/1","title":"Item 1 da licitação 15403205000082014"},"fornecedor":{"href":"/fornecedores/id/fornecedor_pj/02923857000109","title":"Fornecedor 02923857000109: MATRICIAL ENGENHARIA CONSULTIVA"},"licitacao":{"href":"/licitacoes/id/licitacao/15403205000082014","title":"Licitação 15403205000082014"},"modalidade_licitacao":{"href":"/licitacoes/id/modalidade_licitacao/5","title":"Modalidade de Licitação 5: PREGÃO                                            "},"servico":{"href":"/servicos/id/servico/94","title":"Servico 94: ESTUDOS E PROJETOS DE MEIO AMBIENTE - AVALIACAO E ELABORACAODO RELATORIO DE IMPACTO                                     "},"uasg":{"href":"/licitacoes/id/uasg/154032","title":"UASG 154032: UNIVERSIDADE FED. DE CIENCIAS DA SAUDE/RS"}}}]},"count":1}